uuid/__init__.py
uuid/test.py
lib_uuid_porting-2.6.dist-info/LICENSE
lib_uuid_porting-2.6.dist-info/METADATA
lib_uuid_porting-2.6.dist-info/WHEEL
lib_uuid_porting-2.6.dist-info/top_level.txt
lib_uuid_porting-2.6.dist-info/RECORD
