Metadata-Version: 2.1
Name: lib-uuid-porting
Version: 2.6
Summary: Just porting Lib/uuid.py to Python 2.4 and earlier.
